napari_griottes/__init__.py
napari_griottes/_reader.py
napari_griottes/_sample_data.py
napari_griottes/_version.py
napari_griottes/_widget.py
napari_griottes/_writer.py
napari_griottes/napari.yaml
napari_griottes/_tests/__init__.py
napari_griottes/_tests/test_reader.py
napari_griottes/_tests/test_sample_data.py
napari_griottes/_tests/test_widget.py
napari_griottes/_tests/test_writer.py
napari_griottes-0.4.1.dist-info/LICENSE
napari_griottes-0.4.1.dist-info/METADATA
napari_griottes-0.4.1.dist-info/WHEEL
napari_griottes-0.4.1.dist-info/entry_points.txt
napari_griottes-0.4.1.dist-info/top_level.txt
napari_griottes-0.4.1.dist-info/RECORD
