Metadata-Version: 2.1
Name: napari-griottes
Version: 0.4.1
Summary: Create graphs
Home-page: https://github.com/aaristov/napari-griottes
Author: Andrey Aristov
Author-email: aaristov@pasteur.fr
License: BSD-3-Clause
Project-URL: Bug Tracker, https://github.com/aaristov/napari-griottes/issues
Project-URL: Documentation, https://github.com/aaristov/napari-griottes#README.md
Project-URL: Source Code, https://github.com/aaristov/napari-griottes
Project-URL: User Support, https://github.com/aaristov/napari-griottes/issues
Classifier: Development Status :: 2 - Pre-Alpha
Classifier: Framework :: napari
Classifier: Intended Audience :: Developers
Classifier: License :: OSI Approved :: BSD License
Classifier: Operating System :: OS Independent
Classifier: Programming Language :: Python
Classifier: Programming Language :: Python :: 3
Classifier: Programming Language :: Python :: 3 :: Only
Classifier: Programming Language :: Python :: 3.8
Classifier: Programming Language :: Python :: 3.9
Classifier: Programming Language :: Python :: 3.10
Classifier: Topic :: Software Development :: Testing
Requires-Python: >=3.8
License-File: LICENSE
Requires-Dist: griottes
Requires-Dist: networkx
Requires-Dist: numpy
Requires-Dist: pandas (<2)
